dlt_iceberg/__init__.py
dlt_iceberg/adapter.py
dlt_iceberg/destination.py
dlt_iceberg/destination_client.py
dlt_iceberg/error_handling.py
dlt_iceberg/partition_builder.py
dlt_iceberg/schema_casting.py
dlt_iceberg/schema_converter.py
dlt_iceberg/schema_evolution.py
dlt_iceberg/sql_client.py
dlt_iceberg-0.2.0.dist-info/METADATA
dlt_iceberg-0.2.0.dist-info/WHEEL
dlt_iceberg-0.2.0.dist-info/licenses/LICENSE
dlt_iceberg-0.2.0.dist-info/RECORD
