Metadata-Version: 2.4
Name: dlt-iceberg
Version: 0.2.0
Summary: dlt destination for Apache Iceberg with atomic multi-file commits via REST catalogs
Project-URL: Homepage, https://github.com/sidequery/dlt-iceberg
Project-URL: Repository, https://github.com/sidequery/dlt-iceberg
Project-URL: Issues, https://github.com/sidequery/dlt-iceberg/issues
Author-email: Sidequery <hello@sidequery.com>
License: MIT
License-File: LICENSE
Keywords: data-engineering,data-pipeline,dlt,elt,etl,iceberg
Classifier: Development Status :: 4 - Beta
Classifier: Intended Audience :: Developers
Classifier: License :: OSI Approved :: MIT License
Classifier: Programming Language :: Python :: 3
Classifier: Programming Language :: Python :: 3.11
Classifier: Programming Language :: Python :: 3.12
Classifier: Programming Language :: Python :: 3.13
Classifier: Topic :: Database
Classifier: Topic :: Software Development :: Libraries :: Python Modules
Requires-Python: >=3.11
Requires-Dist: boto3>=1.40.50
Requires-Dist: dlt>=1.17.1
Requires-Dist: duckdb>=1.4.3
Requires-Dist: pandas>=2.3.3
Requires-Dist: pyarrow>=21.0.0
Requires-Dist: pydantic<2.11
Requires-Dist: pyiceberg[pyiceberg-core]>=0.10.0
Requires-Dist: requests>=2.32.5
Requires-Dist: s3fs>=0.4.2
Requires-Dist: sqlalchemy>=2.0.44
